Metadata-Version: 1.0
Name: zaagpro
Version: 1.0
Summary: to say the hello world
Home-page: UNKNOWN
Author: UNKNOWN
Author-email: rahulkrishnanfs@gmail.com
License: MIT
Platform: UNKNOWN
